{
  "sysops": [
    {
      "name": "Araisyohei",
      "lastEditId": 90153686,
      "lastEditTimestamp": "2022-06-23T03:07:22Z",
      "lastEventId": 6008897,
      "lastEventTimestamp": "2022-06-21T01:07:50Z"
    },
    {
      "name": "Faso",
      "lastEditId": 90159793,
      "lastEditTimestamp": "2022-06-23T11:14:47Z",
      "lastEventId": 5907169,
      "lastEventTimestamp": "2022-04-10T12:42:14Z"
    },
    {
      "name": "Halowand",
      "lastEditId": 90149717,
      "lastEditTimestamp": "2022-06-22T18:19:51Z",
      "lastEventId": 6011624,
      "lastEventTimestamp": "2022-06-22T17:50:01Z"
    },
    {
      "name": "Infinite0694",
      "lastEditId": 89720035,
      "lastEditTimestamp": "2022-05-27T15:12:47Z",
      "lastEventId": 5975186,
      "lastEventTimestamp": "2022-05-27T15:05:43Z"
    },
    {
      "name": "Jkr2255",
      "lastEditId": 90112491,
      "lastEditTimestamp": "2022-06-20T11:18:15Z",
      "lastEventId": 6005110,
      "lastEventTimestamp": "2022-06-18T12:03:35Z"
    },
    {
      "name": "Kanjy",
      "lastEditId": 89368512,
      "lastEditTimestamp": "2022-05-05T06:03:03Z",
      "lastEventId": 5873832,
      "lastEventTimestamp": "2022-03-21T10:58:39Z"
    },
    {
      "name": "Kinori",
      "lastEditId": 90134538,
      "lastEditTimestamp": "2022-06-21T18:49:58Z",
      "lastEventId": 5976382,
      "lastEventTimestamp": "2022-05-28T10:46:37Z"
    },
    {
      "name": "Kubou",
      "lastEditId": 90028125,
      "lastEditTimestamp": "2022-06-15T04:07:05Z",
      "lastEventId": 6004805,
      "lastEventTimestamp": "2022-06-18T07:04:27Z"
    },
    {
      "name": "Kurihaya",
      "lastEditId": 90163029,
      "lastEditTimestamp": "2022-06-23T14:07:41Z",
      "lastEventId": 6012790,
      "lastEventTimestamp": "2022-06-23T14:05:55Z"
    },
    {
      "name": "Marine-Blue",
      "lastEditId": 90164381,
      "lastEditTimestamp": "2022-06-23T15:55:36Z",
      "lastEventId": 6013001,
      "lastEventTimestamp": "2022-06-23T16:58:21Z"
    },
    {
      "name": "MaximusM4",
      "lastEditId": 90003276,
      "lastEditTimestamp": "2022-06-13T09:48:08Z",
      "lastEventId": 5997961,
      "lastEventTimestamp": "2022-06-13T09:47:16Z"
    },
    {
      "name": "Miya",
      "lastEditId": 90021989,
      "lastEditTimestamp": "2022-06-14T14:49:42Z",
      "lastEventId": 5978274,
      "lastEventTimestamp": "2022-05-29T12:00:34Z"
    },
    {
      "name": "Mobnoboka",
      "lastEditId": 89992265,
      "lastEditTimestamp": "2022-06-12T13:36:45Z",
      "lastEventId": 5967503,
      "lastEventTimestamp": "2022-05-22T13:43:00Z"
    },
    {
      "name": "Muyo",
      "lastEditId": 90163772,
      "lastEditTimestamp": "2022-06-23T14:55:12Z",
      "lastEventId": 6012883,
      "lastEventTimestamp": "2022-06-23T15:46:15Z"
    },
    {
      "name": "Nnh",
      "lastEditId": 90164575,
      "lastEditTimestamp": "2022-06-23T16:13:51Z",
      "lastEventId": 6012641,
      "lastEventTimestamp": "2022-06-23T12:04:24Z"
    },
    {
      "name": "Ohgi",
      "lastEditId": 90132422,
      "lastEditTimestamp": "2022-06-21T15:09:58Z",
      "lastEventId": 6012878,
      "lastEventTimestamp": "2022-06-23T15:36:39Z"
    },
    {
      "name": "Panpulha",
      "lastEditId": 89818544,
      "lastEditTimestamp": "2022-06-03T07:17:23Z",
      "lastEventId": 5914243,
      "lastEventTimestamp": "2022-04-15T15:20:07Z"
    },
    {
      "name": "Peccafly",
      "lastEditId": 89645098,
      "lastEditTimestamp": "2022-05-22T14:08:12Z",
      "lastEventId": 4248014,
      "lastEventTimestamp": "2019-03-24T02:14:08Z"
    },
    {
      "name": "Penn Station",
      "lastEditId": 89260246,
      "lastEditTimestamp": "2022-04-29T03:54:15Z",
      "lastEventId": 5933809,
      "lastEventTimestamp": "2022-04-29T07:28:11Z"
    },
    {
      "name": "Sumaru",
      "lastEditId": 90162587,
      "lastEditTimestamp": "2022-06-23T13:45:28Z",
      "lastEventId": 6012772,
      "lastEventTimestamp": "2022-06-23T13:48:02Z"
    },
    {
      "name": "Taisyo",
      "lastEditId": 90158526,
      "lastEditTimestamp": "2022-06-23T09:55:11Z",
      "lastEventId": 6005347,
      "lastEventTimestamp": "2022-06-18T14:41:53Z"
    },
    {
      "name": "VZP10224",
      "lastEditId": 90145110,
      "lastEditTimestamp": "2022-06-22T12:18:59Z",
      "lastEventId": 6011100,
      "lastEventTimestamp": "2022-06-22T12:10:18Z"
    },
    {
      "name": "W.CC",
      "lastEditId": 90160650,
      "lastEditTimestamp": "2022-06-23T12:04:36Z",
      "lastEventId": 6012458,
      "lastEventTimestamp": "2022-06-23T10:15:49Z"
    },
    {
      "name": "Y-dash",
      "lastEditId": 89691704,
      "lastEditTimestamp": "2022-05-25T21:49:18Z",
      "lastEventId": 5987509,
      "lastEventTimestamp": "2022-06-05T18:47:19Z"
    },
    {
      "name": "Yapparina",
      "lastEditId": 90161207,
      "lastEditTimestamp": "2022-06-23T12:28:53Z",
      "lastEventId": 6006398,
      "lastEventTimestamp": "2022-06-19T09:20:13Z"
    },
    {
      "name": "えのきだたもつ",
      "lastEditId": 90165570,
      "lastEditTimestamp": "2022-06-23T18:36:12Z",
      "lastEventId": 6013009,
      "lastEventTimestamp": "2022-06-23T17:17:08Z"
    },
    {
      "name": "おはぐろ蜻蛉",
      "lastEditId": 90130354,
      "lastEditTimestamp": "2022-06-21T13:05:10Z",
      "lastEventId": 6010669,
      "lastEventTimestamp": "2022-06-22T05:27:09Z"
    },
    {
      "name": "さかおり",
      "lastEditId": 90160347,
      "lastEditTimestamp": "2022-06-23T11:45:28Z",
      "lastEventId": 6012803,
      "lastEventTimestamp": "2022-06-23T14:17:24Z"
    },
    {
      "name": "アルトクール",
      "lastEditId": 90124109,
      "lastEditTimestamp": "2022-06-21T05:41:11Z",
      "lastEventId": 6009192,
      "lastEventTimestamp": "2022-06-21T05:41:05Z"
    },
    {
      "name": "ネイ",
      "lastEditId": 90143571,
      "lastEditTimestamp": "2022-06-22T10:27:13Z",
      "lastEventId": 6012865,
      "lastEventTimestamp": "2022-06-23T15:22:34Z"
    },
    {
      "name": "㭍月例祭",
      "lastEditId": 90164928,
      "lastEditTimestamp": "2022-06-23T16:56:54Z",
      "lastEventId": 6009050,
      "lastEventTimestamp": "2022-06-21T03:47:25Z"
    },
    {
      "name": "伊佐坂安物",
      "lastEditId": 90056731,
      "lastEditTimestamp": "2022-06-17T03:00:18Z",
      "lastEventId": 5995467,
      "lastEventTimestamp": "2022-06-11T12:38:51Z"
    },
    {
      "name": "健ちゃん",
      "lastEditId": 90164834,
      "lastEditTimestamp": "2022-06-23T16:44:27Z",
      "lastEventId": 6012975,
      "lastEventTimestamp": "2022-06-23T16:23:23Z"
    },
    {
      "name": "多摩に暇人",
      "lastEditId": 90033852,
      "lastEditTimestamp": "2022-06-15T11:03:21Z",
      "lastEventId": 5594919,
      "lastEventTimestamp": "2021-09-13T12:03:10Z"
    },
    {
      "name": "東京特許許可局",
      "lastEditId": 90086691,
      "lastEditTimestamp": "2022-06-19T00:08:04Z",
      "lastEventId": 4792100,
      "lastEventTimestamp": "2020-05-16T02:50:58Z"
    },
    {
      "name": "柏尾菓子",
      "lastEditId": 90160819,
      "lastEditTimestamp": "2022-06-23T12:12:44Z",
      "lastEventId": 6012633,
      "lastEventTimestamp": "2022-06-23T11:59:01Z"
    },
    {
      "name": "玄海093",
      "lastEditId": 90088295,
      "lastEditTimestamp": "2022-06-19T02:29:13Z",
      "lastEventId": 6005900,
      "lastEventTimestamp": "2022-06-19T02:51:13Z"
    },
    {
      "name": "霧木諒二",
      "lastEditId": 89990276,
      "lastEditTimestamp": "2022-06-12T11:09:20Z",
      "lastEventId": 5996659,
      "lastEventTimestamp": "2022-06-12T09:26:24Z"
    },
    {
      "name": "青子守歌",
      "lastEditId": 90089646,
      "lastEditTimestamp": "2022-06-19T04:07:10Z",
      "lastEventId": 6004573,
      "lastEventTimestamp": "2022-06-18T03:06:29Z"
    }
  ],
  "rollbackers": [
    {
      "name": "20041027 tatsu",
      "lastEditId": 90144866,
      "lastEditTimestamp": "2022-06-22T12:03:49Z",
      "lastEventId": 6011092,
      "lastEventTimestamp": "2022-06-22T12:03:53Z"
    },
    {
      "name": "5gsheep",
      "lastEditId": 90163053,
      "lastEditTimestamp": "2022-06-23T14:09:48Z",
      "lastEventId": 6012404,
      "lastEventTimestamp": "2022-06-23T09:21:51Z"
    },
    {
      "name": "Ansui",
      "lastEditId": 89794185,
      "lastEditTimestamp": "2022-06-01T13:29:34Z",
      "lastEventId": 5859208,
      "lastEventTimestamp": "2022-03-13T12:14:31Z"
    },
    {
      "name": "Bonfire12",
      "lastEditId": 87900625,
      "lastEditTimestamp": "2022-02-06T08:29:37Z",
      "lastEventId": 5352801,
      "lastEventTimestamp": "2021-04-23T07:10:25Z"
    },
    {
      "name": "Buntschann",
      "lastEditId": 90151090,
      "lastEditTimestamp": "2022-06-22T22:59:02Z",
      "lastEventId": 5843559,
      "lastEventTimestamp": "2022-03-05T02:08:44Z"
    },
    {
      "name": "Chatama",
      "lastEditId": 87186594,
      "lastEditTimestamp": "2021-12-25T10:06:18Z",
      "lastEventId": 4762919,
      "lastEventTimestamp": "2020-04-29T04:52:11Z"
    },
    {
      "name": "Dragoniez",
      "lastEditId": 90160531,
      "lastEditTimestamp": "2022-06-23T11:58:24Z",
      "lastEventId": 6012397,
      "lastEventTimestamp": "2022-06-23T09:17:07Z"
    },
    {
      "name": "Hisagi",
      "lastEditId": 89977191,
      "lastEditTimestamp": "2022-06-11T14:34:55Z",
      "lastEventId": 5970587,
      "lastEventTimestamp": "2022-05-24T17:23:08Z"
    },
    {
      "name": "Jishinni",
      "lastEditId": 87787510,
      "lastEditTimestamp": "2022-01-30T09:28:28Z",
      "lastEventId": 5790582,
      "lastEventTimestamp": "2022-01-30T09:09:45Z"
    },
    {
      "name": "K2-18",
      "lastEditId": 90074545,
      "lastEditTimestamp": "2022-06-18T05:54:52Z",
      "lastEventId": 6012697,
      "lastEventTimestamp": "2022-06-23T12:54:17Z"
    },
    {
      "name": "Kahusi",
      "lastEditId": 89763095,
      "lastEditTimestamp": "2022-05-30T10:29:45Z",
      "lastEventId": 5141585,
      "lastEventTimestamp": "2020-12-20T05:28:47Z"
    },
    {
      "name": "Kanashimi",
      "lastEditId": 90126084,
      "lastEditTimestamp": "2022-06-21T08:28:32Z",
      "lastEventId": 5792328,
      "lastEventTimestamp": "2022-01-31T14:06:56Z"
    },
    {
      "name": "Karasunoko",
      "lastEditId": 90036339,
      "lastEditTimestamp": "2022-06-15T13:48:25Z",
      "lastEventId": 6001181,
      "lastEventTimestamp": "2022-06-15T13:45:51Z"
    },
    {
      "name": "Kocgs",
      "lastEditId": 89948045,
      "lastEditTimestamp": "2022-06-10T06:40:28Z",
      "lastEventId": 5824335,
      "lastEventTimestamp": "2022-02-22T00:43:24Z"
    },
    {
      "name": "Kokoko-H",
      "lastEditId": 89866940,
      "lastEditTimestamp": "2022-06-06T04:31:59Z",
      "lastEventId": 5896552,
      "lastEventTimestamp": "2022-04-03T10:13:20Z"
    },
    {
      "name": "Krorokeroro",
      "lastEditId": 90165486,
      "lastEditTimestamp": "2022-06-23T18:22:06Z",
      "lastEventId": 6007444,
      "lastEventTimestamp": "2022-06-20T05:05:23Z"
    },
    {
      "name": "Lanwi1",
      "lastEditId": 90024682,
      "lastEditTimestamp": "2022-06-14T22:21:58Z",
      "lastEventId": 5985908,
      "lastEventTimestamp": "2022-06-04T13:47:26Z"
    },
    {
      "name": "Mirinano",
      "lastEditId": 90074274,
      "lastEditTimestamp": "2022-06-18T05:36:02Z",
      "lastEventId": 6004709,
      "lastEventTimestamp": "2022-06-18T05:24:09Z"
    },
    {
      "name": "Q8j",
      "lastEditId": 90146600,
      "lastEditTimestamp": "2022-06-22T13:50:35Z",
      "lastEventId": 5992624,
      "lastEventTimestamp": "2022-06-09T11:36:07Z"
    },
    {
      "name": "Sai10ukazuki",
      "lastEditId": 90164648,
      "lastEditTimestamp": "2022-06-23T16:22:41Z",
      "lastEventId": 6012923,
      "lastEventTimestamp": "2022-06-23T16:22:41Z"
    },
    {
      "name": "Siwamura",
      "lastEditId": 89621833,
      "lastEditTimestamp": "2022-05-21T07:20:09Z",
      "lastEventId": 5960098,
      "lastEventTimestamp": "2022-05-17T04:08:05Z"
    },
    {
      "name": "Tail furry",
      "lastEditId": 90147134,
      "lastEditTimestamp": "2022-06-22T14:25:21Z",
      "lastEventId": 6007296,
      "lastEventTimestamp": "2022-06-20T02:26:56Z"
    },
    {
      "name": "Therru2021",
      "lastEditId": 90157903,
      "lastEditTimestamp": "2022-06-23T09:09:08Z",
      "lastEventId": 5930267,
      "lastEventTimestamp": "2022-04-26T22:11:16Z"
    },
    {
      "name": "W7401898",
      "lastEditId": 90154861,
      "lastEditTimestamp": "2022-06-23T05:50:43Z",
      "lastEventId": 6003969,
      "lastEventTimestamp": "2022-06-17T14:59:41Z"
    },
    {
      "name": "ぱたごん",
      "lastEditId": 89421349,
      "lastEditTimestamp": "2022-05-08T06:50:40Z",
      "lastEventId": 5715204,
      "lastEventTimestamp": "2021-12-08T12:28:50Z"
    },
    {
      "name": "みちまん",
      "lastEditId": 89457780,
      "lastEditTimestamp": "2022-05-10T15:00:07Z",
      "lastEventId": 5629495,
      "lastEventTimestamp": "2021-10-08T23:05:02Z"
    },
    {
      "name": "もかめーる",
      "lastEditId": 89907794,
      "lastEditTimestamp": "2022-06-08T05:24:41Z",
      "lastEventId": 5990766,
      "lastEventTimestamp": "2022-06-08T05:24:41Z"
    },
    {
      "name": "コヨミヤ",
      "lastEditId": 90156971,
      "lastEditTimestamp": "2022-06-23T08:14:17Z",
      "lastEventId": 6012318,
      "lastEventTimestamp": "2022-06-23T08:15:05Z"
    },
    {
      "name": "バイロン",
      "lastEditId": 90152424,
      "lastEditTimestamp": "2022-06-23T01:02:22Z",
      "lastEventId": 6002393,
      "lastEventTimestamp": "2022-06-16T10:39:53Z"
    },
    {
      "name": "三日月",
      "lastEditId": 90165443,
      "lastEditTimestamp": "2022-06-23T18:14:26Z",
      "lastEventId": 6009842,
      "lastEventTimestamp": "2022-06-21T14:16:38Z"
    },
    {
      "name": "山田晴通",
      "lastEditId": 90164773,
      "lastEditTimestamp": "2022-06-23T16:36:04Z",
      "lastEventId": 6012916,
      "lastEventTimestamp": "2022-06-23T16:11:02Z"
    },
    {
      "name": "松茸",
      "lastEditId": 90153887,
      "lastEditTimestamp": "2022-06-23T03:33:08Z",
      "lastEventId": 5927508,
      "lastEventTimestamp": "2022-04-24T21:54:37Z"
    },
    {
      "name": "舌先現象になります",
      "lastEditId": 90093699,
      "lastEditTimestamp": "2022-06-19T08:33:53Z",
      "lastEventId": 5989797,
      "lastEventTimestamp": "2022-06-07T12:46:03Z"
    },
    {
      "name": "要塞騎士",
      "lastEditId": 90164800,
      "lastEditTimestamp": "2022-06-23T16:38:53Z",
      "lastEventId": 6008851,
      "lastEventTimestamp": "2022-06-21T00:29:03Z"
    }
  ],
  "eliminators": [
    {
      "name": "Jishinni",
      "lastEditId": 87787510,
      "lastEditTimestamp": "2022-01-30T09:28:28Z",
      "lastEventId": 5790582,
      "lastEventTimestamp": "2022-01-30T09:09:45Z"
    },
    {
      "name": "Karasunoko",
      "lastEditId": 90036339,
      "lastEditTimestamp": "2022-06-15T13:48:25Z",
      "lastEventId": 6001181,
      "lastEventTimestamp": "2022-06-15T13:45:51Z"
    },
    {
      "name": "MGA73",
      "lastEditId": 90117713,
      "lastEditTimestamp": "2022-06-20T17:10:38Z",
      "lastEventId": 6013031,
      "lastEventTimestamp": "2022-06-23T17:55:08Z"
    },
    {
      "name": "SeitenBot2",
      "lastEditId": 90163841,
      "lastEditTimestamp": "2022-06-23T15:00:49Z",
      "lastEventId": 6013065,
      "lastEventTimestamp": "2022-06-23T19:02:31Z"
    }
  ],
  "interfaceAdmins": [
    {
      "name": "Dragoniez",
      "lastEditId": 90160531,
      "lastEditTimestamp": "2022-06-23T11:58:24Z",
      "lastEventId": 6012397,
      "lastEventTimestamp": "2022-06-23T09:17:07Z"
    },
    {
      "name": "Infinite0694",
      "lastEditId": 89720035,
      "lastEditTimestamp": "2022-05-27T15:12:47Z",
      "lastEventId": 5975186,
      "lastEventTimestamp": "2022-05-27T15:05:43Z"
    },
    {
      "name": "Jkr2255",
      "lastEditId": 90112491,
      "lastEditTimestamp": "2022-06-20T11:18:15Z",
      "lastEventId": 6005110,
      "lastEventTimestamp": "2022-06-18T12:03:35Z"
    },
    {
      "name": "Marine-Blue",
      "lastEditId": 90164381,
      "lastEditTimestamp": "2022-06-23T15:55:36Z",
      "lastEventId": 6013001,
      "lastEventTimestamp": "2022-06-23T16:58:21Z"
    },
    {
      "name": "Penn Station",
      "lastEditId": 89260246,
      "lastEditTimestamp": "2022-04-29T03:54:15Z",
      "lastEventId": 5933809,
      "lastEventTimestamp": "2022-04-29T07:28:11Z"
    },
    {
      "name": "Sakoppi",
      "lastEditId": 90162053,
      "lastEditTimestamp": "2022-06-23T13:14:41Z",
      "lastEventId": 6005510,
      "lastEventTimestamp": "2022-06-18T17:27:43Z"
    },
    {
      "name": "W.CC",
      "lastEditId": 90160650,
      "lastEditTimestamp": "2022-06-23T12:04:36Z",
      "lastEventId": 6012458,
      "lastEventTimestamp": "2022-06-23T10:15:49Z"
    },
    {
      "name": "Whym",
      "lastEditId": 90114160,
      "lastEditTimestamp": "2022-06-20T12:53:49Z",
      "lastEventId": 5784724,
      "lastEventTimestamp": "2022-01-26T12:36:23Z"
    },
    {
      "name": "Y-dash",
      "lastEditId": 89691704,
      "lastEditTimestamp": "2022-05-25T21:49:18Z",
      "lastEventId": 5987509,
      "lastEventTimestamp": "2022-06-05T18:47:19Z"
    },
    {
      "name": "ネイ",
      "lastEditId": 90143571,
      "lastEditTimestamp": "2022-06-22T10:27:13Z",
      "lastEventId": 6012865,
      "lastEventTimestamp": "2022-06-23T15:22:34Z"
    },
    {
      "name": "青子守歌",
      "lastEditId": 90089646,
      "lastEditTimestamp": "2022-06-19T04:07:10Z",
      "lastEventId": 6004573,
      "lastEventTimestamp": "2022-06-18T03:06:29Z"
    }
  ],
  "lastUpdate": "2022-06-23T19:03:01Z"
}