{
  "sysops": [
    {
      "name": "Araisyohei",
      "lastEditId": 92338501,
      "lastEditTimestamp": "2022-11-08T11:58:05Z",
      "lastEventId": 6207868,
      "lastEventTimestamp": "2022-11-07T15:42:46Z"
    },
    {
      "name": "Dragoniez",
      "lastEditId": 92443891,
      "lastEditTimestamp": "2022-11-15T12:25:31Z",
      "lastEventId": 6217521,
      "lastEventTimestamp": "2022-11-15T10:55:05Z"
    },
    {
      "name": "Faso",
      "lastEditId": 92113756,
      "lastEditTimestamp": "2022-10-25T01:12:50Z",
      "lastEventId": 6190113,
      "lastEventTimestamp": "2022-10-25T02:02:56Z"
    },
    {
      "name": "Halowand",
      "lastEditId": 92462610,
      "lastEditTimestamp": "2022-11-16T16:54:45Z",
      "lastEventId": 6219362,
      "lastEventTimestamp": "2022-11-16T16:54:45Z"
    },
    {
      "name": "Infinite0694",
      "lastEditId": 92242170,
      "lastEditTimestamp": "2022-11-02T12:55:18Z",
      "lastEventId": 6200986,
      "lastEventTimestamp": "2022-11-02T12:52:40Z"
    },
    {
      "name": "Jkr2255",
      "lastEditId": 92459489,
      "lastEditTimestamp": "2022-11-16T12:41:00Z",
      "lastEventId": 6216487,
      "lastEventTimestamp": "2022-11-14T13:43:10Z"
    },
    {
      "name": "Kanjy",
      "lastEditId": 91393325,
      "lastEditTimestamp": "2022-09-10T06:01:30Z",
      "lastEventId": 6095808,
      "lastEventTimestamp": "2022-08-20T06:47:06Z"
    },
    {
      "name": "Kinori",
      "lastEditId": 92462741,
      "lastEditTimestamp": "2022-11-16T17:14:55Z",
      "lastEventId": 6219374,
      "lastEventTimestamp": "2022-11-16T17:14:55Z"
    },
    {
      "name": "Kubou",
      "lastEditId": 92404875,
      "lastEditTimestamp": "2022-11-13T02:15:58Z",
      "lastEventId": 6214444,
      "lastEventTimestamp": "2022-11-13T01:10:11Z"
    },
    {
      "name": "Kurihaya",
      "lastEditId": 92441321,
      "lastEditTimestamp": "2022-11-15T09:25:21Z",
      "lastEventId": 6217312,
      "lastEventTimestamp": "2022-11-15T07:27:37Z"
    },
    {
      "name": "Marine-Blue",
      "lastEditId": 92447304,
      "lastEditTimestamp": "2022-11-15T16:44:24Z",
      "lastEventId": 6219254,
      "lastEventTimestamp": "2022-11-16T15:39:57Z"
    },
    {
      "name": "MaximusM4",
      "lastEditId": 92354595,
      "lastEditTimestamp": "2022-11-09T15:56:41Z",
      "lastEventId": 6096639,
      "lastEventTimestamp": "2022-08-20T19:15:46Z"
    },
    {
      "name": "Miya",
      "lastEditId": 91809891,
      "lastEditTimestamp": "2022-10-06T21:09:23Z",
      "lastEventId": 6090942,
      "lastEventTimestamp": "2022-08-16T15:49:35Z"
    },
    {
      "name": "Mobnoboka",
      "lastEditId": 92400200,
      "lastEditTimestamp": "2022-11-12T16:25:19Z",
      "lastEventId": 6214150,
      "lastEventTimestamp": "2022-11-12T16:25:19Z"
    },
    {
      "name": "Muyo",
      "lastEditId": 92451856,
      "lastEditTimestamp": "2022-11-16T04:06:23Z",
      "lastEventId": 6219249,
      "lastEventTimestamp": "2022-11-16T15:37:26Z"
    },
    {
      "name": "Nnh",
      "lastEditId": 92463151,
      "lastEditTimestamp": "2022-11-16T18:46:47Z",
      "lastEventId": 6219412,
      "lastEventTimestamp": "2022-11-16T18:46:04Z"
    },
    {
      "name": "Ohgi",
      "lastEditId": 92428749,
      "lastEditTimestamp": "2022-11-14T11:17:05Z",
      "lastEventId": 6216344,
      "lastEventTimestamp": "2022-11-14T11:17:05Z"
    },
    {
      "name": "Panpulha",
      "lastEditId": 92310918,
      "lastEditTimestamp": "2022-11-06T13:47:58Z",
      "lastEventId": 6151136,
      "lastEventTimestamp": "2022-09-28T13:27:17Z"
    },
    {
      "name": "Peccafly",
      "lastEditId": 91373561,
      "lastEditTimestamp": "2022-09-09T00:34:45Z",
      "lastEventId": 6177219,
      "lastEventTimestamp": "2022-10-16T17:53:16Z"
    },
    {
      "name": "Penn Station",
      "lastEditId": 92399629,
      "lastEditTimestamp": "2022-11-12T15:42:03Z",
      "lastEventId": 6215191,
      "lastEventTimestamp": "2022-11-13T12:49:49Z"
    },
    {
      "name": "Sumaru",
      "lastEditId": 92459551,
      "lastEditTimestamp": "2022-11-16T12:43:21Z",
      "lastEventId": 6219066,
      "lastEventTimestamp": "2022-11-16T12:42:07Z"
    },
    {
      "name": "Taisyo",
      "lastEditId": 92460897,
      "lastEditTimestamp": "2022-11-16T14:23:32Z",
      "lastEventId": 6211216,
      "lastEventTimestamp": "2022-11-10T11:02:49Z"
    },
    {
      "name": "VZP10224",
      "lastEditId": 92460100,
      "lastEditTimestamp": "2022-11-16T13:13:49Z",
      "lastEventId": 6182123,
      "lastEventTimestamp": "2022-10-19T23:34:43Z"
    },
    {
      "name": "W.CC",
      "lastEditId": 92441076,
      "lastEditTimestamp": "2022-11-15T09:05:35Z",
      "lastEventId": 6217403,
      "lastEventTimestamp": "2022-11-15T09:02:18Z"
    },
    {
      "name": "Y-dash",
      "lastEditId": 91521655,
      "lastEditTimestamp": "2022-09-18T09:55:53Z",
      "lastEventId": 6076179,
      "lastEventTimestamp": "2022-08-06T07:15:02Z"
    },
    {
      "name": "Yapparina",
      "lastEditId": 92386527,
      "lastEditTimestamp": "2022-11-11T21:51:45Z",
      "lastEventId": 6204195,
      "lastEventTimestamp": "2022-11-04T21:12:14Z"
    },
    {
      "name": "えのきだたもつ",
      "lastEditId": 92462746,
      "lastEditTimestamp": "2022-11-16T17:15:31Z",
      "lastEventId": 6219392,
      "lastEventTimestamp": "2022-11-16T17:55:06Z"
    },
    {
      "name": "おはぐろ蜻蛉",
      "lastEditId": 92457726,
      "lastEditTimestamp": "2022-11-16T11:05:36Z",
      "lastEventId": 6217958,
      "lastEventTimestamp": "2022-11-15T18:26:51Z"
    },
    {
      "name": "さかおり",
      "lastEditId": 92453194,
      "lastEditTimestamp": "2022-11-16T05:59:34Z",
      "lastEventId": 6219179,
      "lastEventTimestamp": "2022-11-16T14:38:22Z"
    },
    {
      "name": "アルトクール",
      "lastEditId": 92430898,
      "lastEditTimestamp": "2022-11-14T13:43:54Z",
      "lastEventId": 6215904,
      "lastEventTimestamp": "2022-11-14T04:55:41Z"
    },
    {
      "name": "ネイ",
      "lastEditId": 92000391,
      "lastEditTimestamp": "2022-10-17T10:48:49Z",
      "lastEventId": 6178438,
      "lastEventTimestamp": "2022-10-17T10:24:50Z"
    },
    {
      "name": "㭍月例祭",
      "lastEditId": 92444576,
      "lastEditTimestamp": "2022-11-15T13:07:24Z",
      "lastEventId": 6216368,
      "lastEventTimestamp": "2022-11-14T11:50:06Z"
    },
    {
      "name": "伊佐坂安物",
      "lastEditId": 92354842,
      "lastEditTimestamp": "2022-11-09T16:27:21Z",
      "lastEventId": 6166821,
      "lastEventTimestamp": "2022-10-10T02:25:16Z"
    },
    {
      "name": "健ちゃん",
      "lastEditId": 92459309,
      "lastEditTimestamp": "2022-11-16T12:31:54Z",
      "lastEventId": 6215326,
      "lastEventTimestamp": "2022-11-13T15:06:17Z"
    },
    {
      "name": "多摩に暇人",
      "lastEditId": 92460415,
      "lastEditTimestamp": "2022-11-16T13:42:12Z",
      "lastEventId": 6185800,
      "lastEventTimestamp": "2022-10-22T10:20:32Z"
    },
    {
      "name": "東京特許許可局",
      "lastEditId": 92459741,
      "lastEditTimestamp": "2022-11-16T12:51:45Z",
      "lastEventId": 6106497,
      "lastEventTimestamp": "2022-08-28T05:06:06Z"
    },
    {
      "name": "柏尾菓子",
      "lastEditId": 92459038,
      "lastEditTimestamp": "2022-11-16T12:18:03Z",
      "lastEventId": 6219045,
      "lastEventTimestamp": "2022-11-16T12:29:46Z"
    },
    {
      "name": "玄海093",
      "lastEditId": 92449320,
      "lastEditTimestamp": "2022-11-15T23:59:14Z",
      "lastEventId": 6205329,
      "lastEventTimestamp": "2022-11-05T15:18:34Z"
    },
    {
      "name": "霧木諒二",
      "lastEditId": 92302161,
      "lastEditTimestamp": "2022-11-06T04:31:19Z",
      "lastEventId": 6124032,
      "lastEventTimestamp": "2022-09-10T05:18:55Z"
    },
    {
      "name": "青子守歌",
      "lastEditId": 92423686,
      "lastEditTimestamp": "2022-11-14T04:51:36Z",
      "lastEventId": 6212235,
      "lastEventTimestamp": "2022-11-11T07:18:28Z"
    }
  ],
  "rollbackers": [
    {
      "name": "20041027 tatsu",
      "lastEditId": 92165914,
      "lastEditTimestamp": "2022-10-28T14:34:29Z",
      "lastEventId": 6194610,
      "lastEventTimestamp": "2022-10-28T14:34:29Z"
    },
    {
      "name": "5gsheep",
      "lastEditId": 92461872,
      "lastEditTimestamp": "2022-11-16T15:38:53Z",
      "lastEventId": 6215216,
      "lastEventTimestamp": "2022-11-13T13:10:13Z"
    },
    {
      "name": "Ansui",
      "lastEditId": 89794185,
      "lastEditTimestamp": "2022-06-01T13:29:34Z",
      "lastEventId": 5859208,
      "lastEventTimestamp": "2022-03-13T12:14:31Z"
    },
    {
      "name": "Bonfire12",
      "lastEditId": 92443896,
      "lastEditTimestamp": "2022-11-15T12:25:38Z",
      "lastEventId": 5352801,
      "lastEventTimestamp": "2021-04-23T07:10:25Z"
    },
    {
      "name": "Buntschann",
      "lastEditId": 91957163,
      "lastEditTimestamp": "2022-10-14T14:04:14Z",
      "lastEventId": 6121998,
      "lastEventTimestamp": "2022-09-08T14:42:35Z"
    },
    {
      "name": "Chatama",
      "lastEditId": 87186594,
      "lastEditTimestamp": "2021-12-25T10:06:18Z",
      "lastEventId": 4762919,
      "lastEventTimestamp": "2020-04-29T04:52:11Z"
    },
    {
      "name": "Hisagi",
      "lastEditId": 91575540,
      "lastEditTimestamp": "2022-09-21T22:08:01Z",
      "lastEventId": 5970587,
      "lastEventTimestamp": "2022-05-24T17:23:08Z"
    },
    {
      "name": "Jishinni",
      "lastEditId": 91776235,
      "lastEditTimestamp": "2022-10-04T14:52:26Z",
      "lastEventId": 6114826,
      "lastEventTimestamp": "2022-09-03T11:38:26Z"
    },
    {
      "name": "K2-18",
      "lastEditId": 92445857,
      "lastEditTimestamp": "2022-11-15T14:39:43Z",
      "lastEventId": 6207425,
      "lastEventTimestamp": "2022-11-07T09:02:03Z"
    },
    {
      "name": "Kahusi",
      "lastEditId": 92413835,
      "lastEditTimestamp": "2022-11-13T10:42:41Z",
      "lastEventId": 6205318,
      "lastEventTimestamp": "2022-11-05T15:14:07Z"
    },
    {
      "name": "Kanashimi",
      "lastEditId": 92261763,
      "lastEditTimestamp": "2022-11-03T20:53:29Z",
      "lastEventId": 6214350,
      "lastEventTimestamp": "2022-11-12T23:35:15Z"
    },
    {
      "name": "Karasunoko",
      "lastEditId": 92418081,
      "lastEditTimestamp": "2022-11-13T15:35:43Z",
      "lastEventId": 6215366,
      "lastEventTimestamp": "2022-11-13T15:40:55Z"
    },
    {
      "name": "Kocgs",
      "lastEditId": 92086152,
      "lastEditTimestamp": "2022-10-23T04:12:16Z",
      "lastEventId": 6186962,
      "lastEventTimestamp": "2022-10-23T04:09:12Z"
    },
    {
      "name": "Krorokeroro",
      "lastEditId": 92462585,
      "lastEditTimestamp": "2022-11-16T16:51:39Z",
      "lastEventId": 6213577,
      "lastEventTimestamp": "2022-11-12T07:35:59Z"
    },
    {
      "name": "Lanwi1",
      "lastEditId": 92457033,
      "lastEditTimestamp": "2022-11-16T10:22:13Z",
      "lastEventId": 6218908,
      "lastEventTimestamp": "2022-11-16T10:22:13Z"
    },
    {
      "name": "Mirinano",
      "lastEditId": 92301807,
      "lastEditTimestamp": "2022-11-06T04:01:48Z",
      "lastEventId": 6185797,
      "lastEventTimestamp": "2022-10-22T10:16:34Z"
    },
    {
      "name": "Q8j",
      "lastEditId": 92435434,
      "lastEditTimestamp": "2022-11-15T00:57:13Z",
      "lastEventId": 6165848,
      "lastEventTimestamp": "2022-10-09T08:50:24Z"
    },
    {
      "name": "Sai10ukazuki",
      "lastEditId": 92445892,
      "lastEditTimestamp": "2022-11-15T14:41:50Z",
      "lastEventId": 6216453,
      "lastEventTimestamp": "2022-11-14T13:20:18Z"
    },
    {
      "name": "Sakoppi",
      "lastEditId": 92459991,
      "lastEditTimestamp": "2022-11-16T13:05:24Z",
      "lastEventId": 6214639,
      "lastEventTimestamp": "2022-11-13T04:12:54Z"
    },
    {
      "name": "Siwamura",
      "lastEditId": 92424181,
      "lastEditTimestamp": "2022-11-14T05:32:28Z",
      "lastEventId": 6124693,
      "lastEventTimestamp": "2022-09-10T12:42:09Z"
    },
    {
      "name": "Syunsyunminmin",
      "lastEditId": 92462110,
      "lastEditTimestamp": "2022-11-16T16:00:29Z",
      "lastEventId": 6219284,
      "lastEventTimestamp": "2022-11-16T15:58:35Z"
    },
    {
      "name": "Tail furry",
      "lastEditId": 92460516,
      "lastEditTimestamp": "2022-11-16T13:52:27Z",
      "lastEventId": 6219075,
      "lastEventTimestamp": "2022-11-16T12:53:38Z"
    },
    {
      "name": "Therru2021",
      "lastEditId": 92289961,
      "lastEditTimestamp": "2022-11-05T11:53:27Z",
      "lastEventId": 5930267,
      "lastEventTimestamp": "2022-04-26T22:11:16Z"
    },
    {
      "name": "W7401898",
      "lastEditId": 92012864,
      "lastEditTimestamp": "2022-10-18T08:09:05Z",
      "lastEventId": 6179556,
      "lastEventTimestamp": "2022-10-18T03:47:59Z"
    },
    {
      "name": "ぱたごん",
      "lastEditId": 91953087,
      "lastEditTimestamp": "2022-10-14T09:11:03Z",
      "lastEventId": 5715204,
      "lastEventTimestamp": "2021-12-08T12:28:50Z"
    },
    {
      "name": "みちまん",
      "lastEditId": 92416904,
      "lastEditTimestamp": "2022-11-13T14:00:21Z",
      "lastEventId": 5629495,
      "lastEventTimestamp": "2021-10-08T23:05:02Z"
    },
    {
      "name": "もかめーる",
      "lastEditId": 92266063,
      "lastEditTimestamp": "2022-11-04T05:17:39Z",
      "lastEventId": 6133074,
      "lastEventTimestamp": "2022-09-16T06:17:19Z"
    },
    {
      "name": "コヨミヤ",
      "lastEditId": 92441554,
      "lastEditTimestamp": "2022-11-15T09:45:00Z",
      "lastEventId": 6182505,
      "lastEventTimestamp": "2022-10-20T07:02:09Z"
    },
    {
      "name": "バイロン",
      "lastEditId": 92460538,
      "lastEditTimestamp": "2022-11-16T13:54:29Z",
      "lastEventId": 6214893,
      "lastEventTimestamp": "2022-11-13T08:07:59Z"
    },
    {
      "name": "三日月",
      "lastEditId": 92462302,
      "lastEditTimestamp": "2022-11-16T16:23:51Z",
      "lastEventId": 6219309,
      "lastEventTimestamp": "2022-11-16T16:23:07Z"
    },
    {
      "name": "山田晴通",
      "lastEditId": 92453715,
      "lastEditTimestamp": "2022-11-16T06:46:08Z",
      "lastEventId": 6218667,
      "lastEventTimestamp": "2022-11-16T06:46:08Z"
    },
    {
      "name": "松茸",
      "lastEditId": 92452190,
      "lastEditTimestamp": "2022-11-16T04:32:31Z",
      "lastEventId": 6187051,
      "lastEventTimestamp": "2022-10-23T06:00:59Z"
    },
    {
      "name": "舌先現象になります",
      "lastEditId": 92233814,
      "lastEditTimestamp": "2022-11-02T00:59:39Z",
      "lastEventId": 6125729,
      "lastEventTimestamp": "2022-09-11T03:19:45Z"
    },
    {
      "name": "要塞騎士",
      "lastEditId": 92461935,
      "lastEditTimestamp": "2022-11-16T15:44:46Z",
      "lastEventId": 6216497,
      "lastEventTimestamp": "2022-11-14T13:56:17Z"
    }
  ],
  "eliminators": [
    {
      "name": "Jishinni",
      "lastEditId": 91776235,
      "lastEditTimestamp": "2022-10-04T14:52:26Z",
      "lastEventId": 6114826,
      "lastEventTimestamp": "2022-09-03T11:38:26Z"
    },
    {
      "name": "Karasunoko",
      "lastEditId": 92418081,
      "lastEditTimestamp": "2022-11-13T15:35:43Z",
      "lastEventId": 6215366,
      "lastEventTimestamp": "2022-11-13T15:40:55Z"
    },
    {
      "name": "MGA73",
      "lastEditId": 92368877,
      "lastEditTimestamp": "2022-11-10T15:43:49Z",
      "lastEventId": 6211472,
      "lastEventTimestamp": "2022-11-10T14:57:44Z"
    },
    {
      "name": "SeitenBot2",
      "lastEditId": 92461471,
      "lastEditTimestamp": "2022-11-16T15:01:22Z",
      "lastEventId": 6219188,
      "lastEventTimestamp": "2022-11-16T14:45:32Z"
    }
  ],
  "interfaceAdmins": [
    {
      "name": "Dragoniez",
      "lastEditId": 92443891,
      "lastEditTimestamp": "2022-11-15T12:25:31Z",
      "lastEventId": 6217521,
      "lastEventTimestamp": "2022-11-15T10:55:05Z"
    },
    {
      "name": "Infinite0694",
      "lastEditId": 92242170,
      "lastEditTimestamp": "2022-11-02T12:55:18Z",
      "lastEventId": 6200986,
      "lastEventTimestamp": "2022-11-02T12:52:40Z"
    },
    {
      "name": "Jkr2255",
      "lastEditId": 92459489,
      "lastEditTimestamp": "2022-11-16T12:41:00Z",
      "lastEventId": 6216487,
      "lastEventTimestamp": "2022-11-14T13:43:10Z"
    },
    {
      "name": "Marine-Blue",
      "lastEditId": 92447304,
      "lastEditTimestamp": "2022-11-15T16:44:24Z",
      "lastEventId": 6219254,
      "lastEventTimestamp": "2022-11-16T15:39:57Z"
    },
    {
      "name": "Penn Station",
      "lastEditId": 92399629,
      "lastEditTimestamp": "2022-11-12T15:42:03Z",
      "lastEventId": 6215191,
      "lastEventTimestamp": "2022-11-13T12:49:49Z"
    },
    {
      "name": "Sakoppi",
      "lastEditId": 92459991,
      "lastEditTimestamp": "2022-11-16T13:05:24Z",
      "lastEventId": 6214639,
      "lastEventTimestamp": "2022-11-13T04:12:54Z"
    },
    {
      "name": "W.CC",
      "lastEditId": 92441076,
      "lastEditTimestamp": "2022-11-15T09:05:35Z",
      "lastEventId": 6217403,
      "lastEventTimestamp": "2022-11-15T09:02:18Z"
    },
    {
      "name": "Whym",
      "lastEditId": 92308262,
      "lastEditTimestamp": "2022-11-06T11:14:32Z",
      "lastEventId": 6169317,
      "lastEventTimestamp": "2022-10-11T11:27:27Z"
    },
    {
      "name": "Y-dash",
      "lastEditId": 91521655,
      "lastEditTimestamp": "2022-09-18T09:55:53Z",
      "lastEventId": 6076179,
      "lastEventTimestamp": "2022-08-06T07:15:02Z"
    },
    {
      "name": "ネイ",
      "lastEditId": 92000391,
      "lastEditTimestamp": "2022-10-17T10:48:49Z",
      "lastEventId": 6178438,
      "lastEventTimestamp": "2022-10-17T10:24:50Z"
    },
    {
      "name": "青子守歌",
      "lastEditId": 92423686,
      "lastEditTimestamp": "2022-11-14T04:51:36Z",
      "lastEventId": 6212235,
      "lastEventTimestamp": "2022-11-11T07:18:28Z"
    }
  ],
  "lastUpdate": "2022-11-16T19:02:55Z"
}